nonebot_plugin_mcpic/__init__.py
nonebot_plugin_mcpic/test.py
nonebot_plugin_mcpic-0.1.1.dist-info/LICENSE
nonebot_plugin_mcpic-0.1.1.dist-info/METADATA
nonebot_plugin_mcpic-0.1.1.dist-info/WHEEL
nonebot_plugin_mcpic-0.1.1.dist-info/top_level.txt
nonebot_plugin_mcpic-0.1.1.dist-info/RECORD
