Metadata-Version: 2.1
Name: nonebot-plugin-mcpic
Version: 0.1.1
Summary: 随机发送MC建筑图片
Author-email: wlm3201 <wlm3201@qq.com>
License: MIT License
Project-URL: Homepage, https://github.com/wlm3201/nonebot-plugin-mcpic
Keywords: mcpic
Requires-Python: >=3.8
License-File: LICENSE
Requires-Dist: httpx >=0.26.0
Requires-Dist: nonebot2 >=2.1.3
Requires-Dist: nonebot-adapter-onebot >=2.3.1
